{
  "annotations": {
    "list": [
      {
        "builtIn": 1,
        "datasource": {
          "type": "grafana",
          "uid": "-- Grafana --"
        },
        "enable": true,
        "hide": true,
        "iconColor": "rgba(0, 211, 255, 1)",
        "name": "Annotations & Alerts",
        "type": "dashboard"
      }
    ]
  },
  "editable": true,
  "fiscalYearStartMonth": 0,
  "graphTooltip": 0,
  "id": 22,
  "links": [],
  "liveNow": false,
  "panels": [
    {
      "datasource": {
        "type": "prometheus",
        "uid": "b268e758-a2a3-44b5-b38a-61d7fa005ae5"
      },
      "fieldConfig": {
        "defaults": {
          "color": {
            "mode": "palette-classic"
          },
          "custom": {
            "axisCenteredZero": false,
            "axisColorMode": "text",
            "axisLabel": "",
            "axisPlacement": "auto",
            "barAlignment": 0,
            "drawStyle": "line",
            "fillOpacity": 25,
            "gradientMode": "opacity",
            "hideFrom": {
              "legend": false,
              "tooltip": false,
              "viz": false
            },
            "insertNulls": false,
            "lineInterpolation": "smooth",
            "lineWidth": 2,
            "pointSize": 5,
            "scaleDistribution": {
              "type": "linear"
            },
            "showPoints": "auto",
            "spanNulls": false,
            "stacking": {
              "group": "A",
              "mode": "none"
            },
            "thresholdsStyle": {
              "mode": "off"
            }
          },
          "decimals": 0,
          "mappings": [],
          "thresholds": {
            "mode": "absolute",
            "steps": [
              {
                "color": "green",
                "value": null
              },
              {
                "color": "red",
                "value": 80
              }
            ]
          },
          "unit": "none"
        },
        "overrides": []
      },
      "gridPos": {
        "h": 8,
        "w": 12,
        "x": 0,
        "y": 0
      },
      "id": 4,
      "options": {
        "legend": {
          "calcs": [
            "min"
          ],
          "displayMode": "table",
          "placement": "right",
          "showLegend": true
        },
        "tooltip": {
          "mode": "single",
          "sort": "none"
        }
      },
      "targets": [
        {
          "datasource": {
            "type": "prometheus",
            "uid": "b268e758-a2a3-44b5-b38a-61d7fa005ae5"
          },
          "disableTextWrap": false,
          "editorMode": "code",
          "expr": "sum(kube_pod_status_phase{namespace=\"momo-store\",pod=~\"backend.*\"}) by (phase)",
          "format": "time_series",
          "fullMetaSearch": false,
          "includeNullMetadata": false,
          "instant": false,
          "interval": "",
          "legendFormat": " {{phase}} ",
          "range": true,
          "refId": "A",
          "useBackend": false
        }
      ],
      "title": "Status Pod backend",
      "type": "timeseries"
    },
    {
      "datasource": {
        "type": "prometheus",
        "uid": "b268e758-a2a3-44b5-b38a-61d7fa005ae5"
      },
      "fieldConfig": {
        "defaults": {
          "color": {
            "mode": "palette-classic"
          },
          "custom": {
            "axisCenteredZero": false,
            "axisColorMode": "text",
            "axisLabel": "",
            "axisPlacement": "auto",
            "barAlignment": 0,
            "drawStyle": "line",
            "fillOpacity": 25,
            "gradientMode": "opacity",
            "hideFrom": {
              "legend": false,
              "tooltip": false,
              "viz": false
            },
            "insertNulls": false,
            "lineInterpolation": "smooth",
            "lineWidth": 2,
            "pointSize": 5,
            "scaleDistribution": {
              "type": "linear"
            },
            "showPoints": "auto",
            "spanNulls": false,
            "stacking": {
              "group": "A",
              "mode": "none"
            },
            "thresholdsStyle": {
              "mode": "off"
            }
          },
          "decimals": 0,
          "mappings": [],
          "thresholds": {
            "mode": "absolute",
            "steps": [
              {
                "color": "green",
                "value": null
              },
              {
                "color": "red",
                "value": 80
              }
            ]
          },
          "unit": "none"
        },
        "overrides": []
      },
      "gridPos": {
        "h": 8,
        "w": 12,
        "x": 12,
        "y": 0
      },
      "id": 8,
      "options": {
        "legend": {
          "calcs": [
            "min"
          ],
          "displayMode": "table",
          "placement": "right",
          "showLegend": true
        },
        "tooltip": {
          "mode": "single",
          "sort": "none"
        }
      },
      "targets": [
        {
          "datasource": {
            "type": "prometheus",
            "uid": "b268e758-a2a3-44b5-b38a-61d7fa005ae5"
          },
          "disableTextWrap": false,
          "editorMode": "code",
          "expr": "sum(kube_pod_status_phase{namespace=\"momo-store\",pod=~\"frontend.*\"}) by (phase)",
          "format": "time_series",
          "fullMetaSearch": false,
          "includeNullMetadata": false,
          "instant": false,
          "interval": "",
          "legendFormat": " {{phase}}",
          "range": true,
          "refId": "A",
          "useBackend": false
        }
      ],
      "title": "Status Pod frontend",
      "type": "timeseries"
    },
    {
      "datasource": {
        "type": "prometheus",
        "uid": "b268e758-a2a3-44b5-b38a-61d7fa005ae5"
      },
      "fieldConfig": {
        "defaults": {
          "color": {
            "mode": "palette-classic"
          },
          "custom": {
            "axisCenteredZero": false,
            "axisColorMode": "text",
            "axisLabel": "",
            "axisPlacement": "auto",
            "barAlignment": 0,
            "drawStyle": "line",
            "fillOpacity": 25,
            "gradientMode": "opacity",
            "hideFrom": {
              "legend": false,
              "tooltip": false,
              "viz": false
            },
            "insertNulls": false,
            "lineInterpolation": "smooth",
            "lineWidth": 2,
            "pointSize": 5,
            "scaleDistribution": {
              "type": "linear"
            },
            "showPoints": "auto",
            "spanNulls": false,
            "stacking": {
              "group": "A",
              "mode": "none"
            },
            "thresholdsStyle": {
              "mode": "off"
            }
          },
          "decimals": 0,
          "mappings": [],
          "thresholds": {
            "mode": "absolute",
            "steps": [
              {
                "color": "green",
                "value": null
              },
              {
                "color": "red",
                "value": 80
              }
            ]
          },
          "unit": "none"
        },
        "overrides": []
      },
      "gridPos": {
        "h": 8,
        "w": 12,
        "x": 0,
        "y": 8
      },
      "id": 5,
      "options": {
        "legend": {
          "calcs": [
            "min"
          ],
          "displayMode": "table",
          "placement": "right",
          "showLegend": true
        },
        "tooltip": {
          "mode": "single",
          "sort": "none"
 